odoo9_addon_purchase_order_approved-9.0.1.0.0-py2.7-nspkg.pth
odoo9_addon_purchase_order_approved-9.0.1.0.0.dist-info/DESCRIPTION.rst
odoo9_addon_purchase_order_approved-9.0.1.0.0.dist-info/METADATA
odoo9_addon_purchase_order_approved-9.0.1.0.0.dist-info/RECORD
odoo9_addon_purchase_order_approved-9.0.1.0.0.dist-info/WHEEL
odoo9_addon_purchase_order_approved-9.0.1.0.0.dist-info/metadata.json
odoo9_addon_purchase_order_approved-9.0.1.0.0.dist-info/namespace_packages.txt
odoo9_addon_purchase_order_approved-9.0.1.0.0.dist-info/top_level.txt
odoo_addons/purchase_order_approved/README.rst
odoo_addons/purchase_order_approved/__init__.py
odoo_addons/purchase_order_approved/__openerp__.py
odoo_addons/purchase_order_approved/models/__init__.py
odoo_addons/purchase_order_approved/models/purchase_order.py
odoo_addons/purchase_order_approved/models/res_company.py
odoo_addons/purchase_order_approved/static/description/icon.png
odoo_addons/purchase_order_approved/static/description/schema.png
odoo_addons/purchase_order_approved/views/purchase_order_view.xml
odoo_addons/purchase_order_approved/views/res_company_view.xml
